log2/__init__.py
log2/log2.py
log2/version.py
log2-0.2.1.dist-info/METADATA
log2-0.2.1.dist-info/WHEEL
log2-0.2.1.dist-info/top_level.txt
log2-0.2.1.dist-info/RECORD
